jumpgate/__init__.py
jumpgate/cli.py
jumpgate-0.0.1.dist-info/METADATA
jumpgate-0.0.1.dist-info/WHEEL
jumpgate-0.0.1.dist-info/entry_points.txt
jumpgate-0.0.1.dist-info/RECORD
